MANIFEST.in
setup.py
farmboy/__init__.py
farmboy/aptcacher.py
farmboy/aws.py
farmboy/cli.py
farmboy/core.py
farmboy/default_tasks.py
farmboy/django.py
farmboy/dns.py
farmboy/fabric_.py
farmboy/files.py
farmboy/gitlab.py
farmboy/gunicorn.py
farmboy/haproxy.py
farmboy/jenkins.py
farmboy/mysql.py
farmboy/nginx.py
farmboy/openstack.py
farmboy/socks5.py
farmboy/tomcat.py
farmboy/util.py
farmboy/vagrant.py
farmboy.egg-info/PKG-INFO
farmboy.egg-info/SOURCES.txt
farmboy.egg-info/dependency_links.txt
farmboy.egg-info/entry_points.txt
farmboy.egg-info/requires.txt
farmboy.egg-info/top_level.txt
farmboy/_files/.__init__.py.swp
farmboy/_files/__init__.pyc
farmboy/_files/apt-cacher/01apt-cacher
farmboy/_files/apt-cacher/apt-cacher.conf
farmboy/_files/apt-cacher/default
farmboy/_files/farmboy/fabfile.py.template
farmboy/_files/farmboy/hosts
farmboy/_files/git/gitconfig.gitlab
farmboy/_files/gitlab/database.yml
farmboy/_files/gitlab/gitlab.yml
farmboy/_files/gitlab-shell/config.yml
farmboy/_files/gunicorn/django
farmboy/_files/gunicorn/flask
farmboy/_files/gunicorn/wsgi
farmboy/_files/haproxy/default
farmboy/_files/haproxy/haproxy.base
farmboy/_files/mysql/mysqld.cnf
farmboy/_files/nginx/gitlab
farmboy/_files/nginx/jenkins
farmboy/_files/nginx/web
farmboy/_files/postgres/commands
farmboy/_files/postgres/pg_hba.conf
farmboy/_files/postgres/postgresql.conf
farmboy/_files/vagrant/Vagrantfile