Metadata-Version: 1.0
Name: farmboy
Version: 0.2
Summary: Rapid development environments.
Home-page: https://github.com/termie/farmboy
Author: Andy Smith
Author-email: github@anarkystic.com
License: UNKNOWN
Platform: UNKNOWN
